fluentflet/__init__.py
fluentflet/__version__.py
fluentflet/components/__init__.py
fluentflet/components/background.py
fluentflet/components/button.py
fluentflet/components/calendar.py
fluentflet/components/checkbox.py
fluentflet/components/dialog.py
fluentflet/components/dropdown.py
fluentflet/components/expander.py
fluentflet/components/gridview.py
fluentflet/components/listitem.py
fluentflet/components/progressring.py
fluentflet/components/radio.py
fluentflet/components/slider.py
fluentflet/components/textbox.py
fluentflet/components/toast.py
fluentflet/components/toggle.py
fluentflet/components/tooltip.py
fluentflet/components/treeview.py
fluentflet/utils/__init__.py
fluentflet/utils/apply_window_effects.py
fluentflet/utils/enable_drag_and_drop.py
fluentflet/utils/fluent_design_system.py
fluentflet/utils/fluent_icons.py
fluentflet/utils/runtime_icon_changer.py
fluentflet/window/__init__.py
fluentflet/window/fluent_window.py
fluentflet-0.2.0a1.dist-info/METADATA
fluentflet-0.2.0a1.dist-info/WHEEL
fluentflet-0.2.0a1.dist-info/top_level.txt
fluentflet-0.2.0a1.dist-info/RECORD
