Metadata-Version: 2.1
Name: fluentflet
Version: 0.2.0a1
Summary: Fluent Design System components for Flet
Author: Edoardo Balducci
Author-email: edoardoba2004@gmail.com
License: MIT
Project-URL: Homepage, https://github.com/Bbalduzz/fluentflet
Project-URL: Issues, https://github.com/Bbalduzz/fluentflet/issues
Classifier: Programming Language :: Python :: 3
Classifier: License :: OSI Approved :: MIT License
Classifier: Operating System :: OS Independent
Requires-Python: >=3.7
Requires-Dist: flet >=0.25.2
